Metadata-Version: 1.0
Name: altugssecondtest
Version: 0.2.0
Summary: A Python package example
Home-page: https://altugb@bitbucket.org/altugb/altugssecondtest.git
Author: altugb
Author-email: altug.bitlislioglu@epfl.ch
License: UNKNOWN
Platform: UNKNOWN
